terminal_vault/__init__.py
terminal_vault/__main__.py
terminal_vault/cli/__init__.py
terminal_vault/cli/interactive.py
terminal_vault/cli/main.py
terminal_vault/core/__init__.py
terminal_vault/core/config.py
terminal_vault/core/lockout.py
terminal_vault/core/security.py
terminal_vault/core/vault.py
terminal_vault/plugins/__init__.py
terminal_vault/plugins/base.py
terminal_vault/utils/__init__.py
terminal_vault/utils/batch.py
terminal_vault/utils/logging_utils.py
terminal_vault-0.1.1.dist-info/METADATA
terminal_vault-0.1.1.dist-info/WHEEL
terminal_vault-0.1.1.dist-info/entry_points.txt
terminal_vault-0.1.1.dist-info/top_level.txt
terminal_vault-0.1.1.dist-info/RECORD
