Metadata-Version: 2.4
Name: terminal_vault
Version: 0.1.1
Summary: Terminal Vault CLI for secure notes with tagging and search capabilities
Author: Antigravity
Author-email: "Adnan, Prem" <nness865@gmail.com>
License: MIT
Requires-Python: >=3.8
Dynamic: author
Dynamic: requires-python
